{
  "version": [
    1,
    0
  ],
  "type": "Eco.Gameplay.Civics.Laws.Law",
  "name": "Kattegat Sales Tax",
  "reference": false,
  "description": "Kattegat Sales Tax for development of town infrastructure",
  "properties": {
    "Sections": [
      {
        "type": "Eco.Gameplay.Civics.Laws.LawSection",
        "reference": false,
        "properties": {
          "Title": "Sales Tax",
          "UserDescription": "A flat tax of 2% on all sales within the town. An exception is made for the Town Hall, as well as skillless players actively selling.  It also takes into account companies.",
          "Triggers": [
            {
              "type": "Eco.Gameplay.Civics.Laws.TriggerSettings",
              "reference": false,
              "properties": {
                "Trigger": {
                  "type": "Type",
                  "value": "Eco.Gameplay.GameActions.CurrencyTrade"
                },
                "Configs": [
                  {
                    "type": "Eco.Gameplay.GameActions.SelectTriggerConfig",
                    "typeToConfig": "Eco.Gameplay.GameActions.CurrencyTrade",
                    "propNameBacker": "BankAccount",
                    "propDisplayName": "Bank Account",
                    "properties": {
                      "List": {
                        "type": "GamePickerList",
                        "mustDeriveType": {
                          "type": "Type",
                          "value": "Eco.Gameplay.Economy.BankAccount"
                        },
                        "requiredTag": null,
                        "internalDescription": "Any",
                        "entries": []
                      }
                    }
                  },
                  {
                    "type": "Eco.Gameplay.GameActions.SelectTriggerConfig",
                    "typeToConfig": "Eco.Gameplay.GameActions.CurrencyTrade",
                    "propNameBacker": "Currency",
                    "propDisplayName": "Currency",
                    "properties": {
                      "List": {
                        "type": "GamePickerList",
                        "mustDeriveType": {
                          "type": "Type",
                          "value": "Eco.Gameplay.Economy.Currency"
                        },
                        "requiredTag": null,
                        "internalDescription": "<link=\"view:3914:103248\"><icon name=\"CurrencySymbol\" type=\"nobg\"><style=\"Currency\">Euro</style></icon></link>",
                        "entries": [
                          {
                            "type": "Eco.Gameplay.Economy.Currency",
                            "name": "Euro",
                            "reference": true
                          }
                        ]
                      }
                    }
                  },
                  {
                    "type": "Eco.Gameplay.GameActions.SelectTriggerConfig",
                    "typeToConfig": "Eco.Gameplay.GameActions.CurrencyTrade",
                    "propNameBacker": "ItemUsed",
                    "propDisplayName": "Item Traded",
                    "properties": {
                      "List": {
                        "type": "GamePickerList",
                        "mustDeriveType": {
                          "type": "Type",
                          "value": "Eco.Gameplay.Items.Item"
                        },
                        "requiredTag": null,
                        "internalDescription": "Any",
                        "entries": []
                      }
                    }
                  }
                ]
              }
            }
          ],
          "IfThenBlocks": [
            {
              "type": "Eco.Gameplay.Civics.IfThenBlock",
              "reference": false,
              "properties": {
                "If": {
                  "type": "Eco.Gameplay.Civics.GameValues.SetOfConditions",
                  "properties": {
                    "List": [
                      {
                        "type": "Eco.Gameplay.Civics.GameValues.SetOfConditions",
                        "properties": {
                          "List": [
                            {
                              "type": "Eco.Gameplay.Civics.GameValues.SetOfConditions",
                              "properties": {
                                "List": [
                                  {
                                    "type": "GameValueContext",
                                    "_name": "Selling",
                                    "markedUpName": "<icon name=\"CurrencyTrade\" type=\"\">Selling</icon>",
                                    "contextDescription": "<i>Was the good bought or sold by the initiating player?</i>"
                                  },
                                  {
                                    "type": "Eco.Gameplay.Civics.GameValues.Compare",
                                    "properties": {
                                      "Left": {
                                        "type": "Eco.Mods.LawExtensions.CitizenSkillCount",
                                        "properties": {
                                          "Citizen": {
                                            "type": "GameValueContext",
                                            "_name": "Citizen",
                                            "markedUpName": "<icon name=\"User\" type=\"\">Citizen</icon>",
                                            "contextDescription": "<i>The citizen who performed the interaction.</i>"
                                          },
                                          "IncludeUnspecialised": {
                                            "type": "Eco.Gameplay.Civics.GameValues.No",
                                            "properties": {}
                                          }
                                        }
                                      },
                                      "Comparison": "GreaterThan",
                                      "Right": {
                                        "type": "GameValueWrapper",
                                        "value": 1.0
                                      }
                                    }
                                  }
                                ],
                                "Comparison": "All"
                              }
                            },
                            {
                              "type": "Eco.Gameplay.Civics.GameValues.SetOfConditions",
                              "properties": {
                                "List": [
                                  {
                                    "type": "GameValueContext",
                                    "_name": "Buying",
                                    "markedUpName": "<icon name=\"CurrencyTrade\" type=\"\">Buying</icon>",
                                    "contextDescription": "<i>Was the good bought or sold by the initiating player?</i>"
                                  },
                                  {
                                    "type": "Eco.Gameplay.Civics.GameValues.Values.DistrictRequirements",
                                    "properties": {
                                      "Location": {
                                        "type": "GameValueContext",
                                        "_name": "Action Location",
                                        "markedUpName": "<icon name=\"CurrencyTrade\" type=\"\">Action Location</icon>",
                                        "contextDescription": "<i>The position where the interaction took place.</i>"
                                      },
                                      "Districts": {
                                        "type": "GamePickerList",
                                        "mustDeriveType": {
                                          "type": "Type",
                                          "value": "Eco.Gameplay.LegislationSystem.District"
                                        },
                                        "requiredTag": null,
                                        "internalDescription": "<link=\"view:3396:46184967\"><icon name=\"District\" type=\"\"><color=#BEB769FF>Offices of the Governments of the States</color></icon></link>",
                                        "entries": [
                                          {
                                            "type": "Eco.Gameplay.LegislationSystem.District",
                                            "name": "Offices of the Governments of the States",
                                            "reference": true
                                          }
                                        ]
                                      },
                                      "Requirements": "OutsideAll"
                                    }
                                  }
                                ],
                                "Comparison": "All"
                              }
                            }
                          ],
                          "Comparison": "Any"
                        }
                      }
                    ],
                    "Comparison": "All"
                  }
                },
                "Then": [
                  {
                    "type": "Eco.Gameplay.Civics.LegalActions.Conditional_LegalAction",
                    "reference": false,
                    "properties": {
                      "IfThenBlock": {
                        "type": "Eco.Gameplay.Civics.IfThenBlock",
                        "reference": false,
                        "properties": {
                          "If": {
                            "type": "Eco.Gameplay.Civics.GameValues.SetOfConditions",
                            "properties": {
                              "List": [
                                {
                                  "type": "Eco.Mods.Companies.IsCompanyLegalPerson",
                                  "properties": {
                                    "Citizen": {
                                      "type": "GameValueContext",
                                      "_name": "Seller",
                                      "markedUpName": "<icon name=\"User\" type=\"\">Seller</icon>",
                                      "contextDescription": "<i>The selling player.</i>"
                                    }
                                  }
                                },
                                {
                                  "type": "Eco.Mods.Companies.IsEmployeeOfCompany",
                                  "properties": {
                                    "Citizen": {
                                      "type": "GameValueContext",
                                      "_name": "Seller",
                                      "markedUpName": "<icon name=\"User\" type=\"\">Seller</icon>",
                                      "contextDescription": "<i>The selling player.</i>"
                                    }
                                  }
                                }
                              ],
                              "Comparison": "None"
                            }
                          },
                          "Then": [
                            {
                              "type": "Eco.Mods.SmartTax.SmartTax_LegalAction",
                              "reference": false,
                              "properties": {
                                "TargetBankAccount": {
                                  "type": "GameValueWrapper",
                                  "value": {
                                    "type": "Eco.Gameplay.Economy.TreasuryBankAccount",
                                    "name": "Kattegat Treasury",
                                    "reference": true
                                  }
                                },
                                "Currency": {
                                  "type": "GameValueWrapper",
                                  "value": {
                                    "type": "Eco.Gameplay.Economy.Currency",
                                    "name": "Euro",
                                    "reference": true
                                  }
                                },
                                "Amount": {
                                  "type": "Eco.Gameplay.Civics.GameValues.Percent_GameValue",
                                  "properties": {
                                    "Number": {
                                      "type": "GameValueContext",
                                      "_name": "Currency Amount",
                                      "markedUpName": "<icon name=\"CurrencyTrade\" type=\"\">Currency Amount</icon>",
                                      "contextDescription": "<i>Amount used in the transaction.</i>"
                                    },
                                    "Percent": {
                                      "type": "GameValueWrapper",
                                      "value": 2.0
                                    }
                                  }
                                },
                                "Target": {
                                  "type": "GameValueContext",
                                  "_name": "Seller",
                                  "markedUpName": "<icon name=\"User\" type=\"\">Seller</icon>",
                                  "contextDescription": "<i>The selling player.</i>"
                                },
                                "TaxCode": "KattegatSalesTax",
                                "Suspended": {
                                  "type": "Eco.Gameplay.Civics.GameValues.No",
                                  "properties": {}
                                },
                                "Silent": {
                                  "type": "Eco.Gameplay.Civics.GameValues.Yes",
                                  "properties": {}
                                },
                                "InfoboxOnSuccess": {
                                  "type": "Eco.Gameplay.Civics.GameValues.Yes",
                                  "properties": {}
                                }
                              }
                            }
                          ]
                        }
                      },
                      "InfoboxOnSuccess": {
                        "type": "Eco.Gameplay.Civics.GameValues.Yes",
                        "properties": {}
                      }
                    }
                  },
                  {
                    "type": "Eco.Gameplay.Civics.LegalActions.Conditional_LegalAction",
                    "reference": false,
                    "properties": {
                      "IfThenBlock": {
                        "type": "Eco.Gameplay.Civics.IfThenBlock",
                        "reference": false,
                        "properties": {
                          "If": {
                            "type": "Eco.Gameplay.Civics.GameValues.SetOfConditions",
                            "properties": {
                              "List": [
                                {
                                  "type": "Eco.Mods.Companies.IsCompanyLegalPerson",
                                  "properties": {
                                    "Citizen": {
                                      "type": "GameValueContext",
                                      "_name": "Seller",
                                      "markedUpName": "<icon name=\"User\" type=\"\">Seller</icon>",
                                      "contextDescription": "<i>The selling player.</i>"
                                    }
                                  }
                                }
                              ],
                              "Comparison": "All"
                            }
                          },
                          "Then": [
                            {
                              "type": "Eco.Mods.SmartTax.SmartTax_LegalAction",
                              "reference": false,
                              "properties": {
                                "TargetBankAccount": {
                                  "type": "GameValueWrapper",
                                  "value": {
                                    "type": "Eco.Gameplay.Economy.TreasuryBankAccount",
                                    "name": "Kattegat Treasury",
                                    "reference": true
                                  }
                                },
                                "Currency": {
                                  "type": "GameValueWrapper",
                                  "value": {
                                    "type": "Eco.Gameplay.Economy.Currency",
                                    "name": "Euro",
                                    "reference": true
                                  }
                                },
                                "Amount": {
                                  "type": "Eco.Gameplay.Civics.GameValues.Percent_GameValue",
                                  "properties": {
                                    "Number": {
                                      "type": "Eco.Gameplay.Civics.GameValues.Percent_GameValue",
                                      "properties": {
                                        "Number": {
                                          "type": "GameValueContext",
                                          "_name": "Currency Amount",
                                          "markedUpName": "<icon name=\"CurrencyTrade\" type=\"\">Currency Amount</icon>",
                                          "contextDescription": "<i>Amount used in the transaction.</i>"
                                        },
                                        "Percent": {
                                          "type": "Eco.Gameplay.Civics.GameValues.Arithmetic",
                                          "properties": {
                                            "LeftNumber": {
                                              "type": "GameValueWrapper",
                                              "value": 100.0
                                            },
                                            "Operation": "Subtract",
                                            "RightNumber": {
                                              "type": "Eco.Gameplay.Civics.GameValues.Values.Stats.CustomStatQuery",
                                              "properties": {
                                                "CustomStatName": "companyTaxRate",
                                                "Settlement": {
                                                  "type": "GameValueWrapper",
                                                  "value": {
                                                    "type": "Eco.Gameplay.Settlements.Settlement",
                                                    "name": "The Federation of White Tiger",
                                                    "reference": true
                                                  }
                                                },
                                                "TimeRangeInHours": {
                                                  "type": "GameValueWrapper",
                                                  "value": 0.0
                                                },
                                                "TimeRangeType": "CurrentTimeBlock",
                                                "User": {
                                                  "type": "GameValueContext",
                                                  "_name": "Seller",
                                                  "markedUpName": "<icon name=\"User\" type=\"\">Seller</icon>",
                                                  "contextDescription": "<i>The selling player.</i>"
                                                }
                                              }
                                            }
                                          }
                                        }
                                      }
                                    },
                                    "Percent": {
                                      "type": "GameValueWrapper",
                                      "value": 2.0
                                    }
                                  }
                                },
                                "Target": {
                                  "type": "GameValueContext",
                                  "_name": "Seller",
                                  "markedUpName": "<icon name=\"User\" type=\"\">Seller</icon>",
                                  "contextDescription": "<i>The selling player.</i>"
                                },
                                "TaxCode": "KattegatSalesTax",
                                "Suspended": {
                                  "type": "Eco.Gameplay.Civics.GameValues.No",
                                  "properties": {}
                                },
                                "Silent": {
                                  "type": "Eco.Gameplay.Civics.GameValues.Yes",
                                  "properties": {}
                                },
                                "InfoboxOnSuccess": {
                                  "type": "Eco.Gameplay.Civics.GameValues.Yes",
                                  "properties": {}
                                }
                              }
                            }
                          ]
                        }
                      },
                      "InfoboxOnSuccess": {
                        "type": "Eco.Gameplay.Civics.GameValues.Yes",
                        "properties": {}
                      }
                    }
                  },
                  {
                    "type": "Eco.Gameplay.Civics.LegalActions.Conditional_LegalAction",
                    "reference": false,
                    "properties": {
                      "IfThenBlock": {
                        "type": "Eco.Gameplay.Civics.IfThenBlock",
                        "reference": false,
                        "properties": {
                          "If": {
                            "type": "Eco.Gameplay.Civics.GameValues.SetOfConditions",
                            "properties": {
                              "List": [
                                {
                                  "type": "Eco.Mods.Companies.IsEmployeeOfCompany",
                                  "properties": {
                                    "Citizen": {
                                      "type": "GameValueContext",
                                      "_name": "Seller",
                                      "markedUpName": "<icon name=\"User\" type=\"\">Seller</icon>",
                                      "contextDescription": "<i>The selling player.</i>"
                                    }
                                  }
                                }
                              ],
                              "Comparison": "All"
                            }
                          },
                          "Then": [
                            {
                              "type": "Eco.Mods.SmartTax.SmartTax_LegalAction",
                              "reference": false,
                              "properties": {
                                "TargetBankAccount": {
                                  "type": "GameValueWrapper",
                                  "value": {
                                    "type": "Eco.Gameplay.Economy.TreasuryBankAccount",
                                    "name": "Kattegat Treasury",
                                    "reference": true
                                  }
                                },
                                "Currency": {
                                  "type": "GameValueWrapper",
                                  "value": {
                                    "type": "Eco.Gameplay.Economy.Currency",
                                    "name": "Euro",
                                    "reference": true
                                  }
                                },
                                "Amount": {
                                  "type": "Eco.Gameplay.Civics.GameValues.Percent_GameValue",
                                  "properties": {
                                    "Number": {
                                      "type": "Eco.Gameplay.Civics.GameValues.Percent_GameValue",
                                      "properties": {
                                        "Number": {
                                          "type": "GameValueContext",
                                          "_name": "Currency Amount",
                                          "markedUpName": "<icon name=\"CurrencyTrade\" type=\"\">Currency Amount</icon>",
                                          "contextDescription": "<i>Amount used in the transaction.</i>"
                                        },
                                        "Percent": {
                                          "type": "Eco.Gameplay.Civics.GameValues.Arithmetic",
                                          "properties": {
                                            "LeftNumber": {
                                              "type": "GameValueWrapper",
                                              "value": 100.0
                                            },
                                            "Operation": "Subtract",
                                            "RightNumber": {
                                              "type": "Eco.Gameplay.Civics.GameValues.Values.Stats.CustomStatQuery",
                                              "properties": {
                                                "CustomStatName": "companyTaxRate",
                                                "Settlement": {
                                                  "type": "GameValueWrapper",
                                                  "value": {
                                                    "type": "Eco.Gameplay.Settlements.Settlement",
                                                    "name": "The Federation of White Tiger",
                                                    "reference": true
                                                  }
                                                },
                                                "TimeRangeInHours": {
                                                  "type": "GameValueWrapper",
                                                  "value": 0.0
                                                },
                                                "TimeRangeType": "CurrentTimeBlock",
                                                "User": {
                                                  "type": "Eco.Mods.Companies.EmployerLegalPerson",
                                                  "properties": {
                                                    "Citizen": {
                                                      "type": "GameValueContext",
                                                      "_name": "Seller",
                                                      "markedUpName": "<icon name=\"User\" type=\"\">Seller</icon>",
                                                      "contextDescription": "<i>The selling player.</i>"
                                                    }
                                                  }
                                                }
                                              }
                                            }
                                          }
                                        }
                                      }
                                    },
                                    "Percent": {
                                      "type": "GameValueWrapper",
                                      "value": 2.0
                                    }
                                  }
                                },
                                "Target": {
                                  "type": "Eco.Mods.Companies.EmployerLegalPersonAlias",
                                  "properties": {
                                    "Citizen": {
                                      "type": "GameValueContext",
                                      "_name": "Seller",
                                      "markedUpName": "<icon name=\"User\" type=\"\">Seller</icon>",
                                      "contextDescription": "<i>The selling player.</i>"
                                    }
                                  }
                                },
                                "TaxCode": "KattegatSalesTax",
                                "Suspended": {
                                  "type": "Eco.Gameplay.Civics.GameValues.No",
                                  "properties": {}
                                },
                                "Silent": {
                                  "type": "Eco.Gameplay.Civics.GameValues.Yes",
                                  "properties": {}
                                },
                                "InfoboxOnSuccess": {
                                  "type": "Eco.Gameplay.Civics.GameValues.Yes",
                                  "properties": {}
                                }
                              }
                            }
                          ]
                        }
                      },
                      "InfoboxOnSuccess": {
                        "type": "Eco.Gameplay.Civics.GameValues.Yes",
                        "properties": {}
                      }
                    }
                  }
                ]
              }
            }
          ]
        }
      }
    ],
    "State": "Active"
  }
}